lowmovers/__init__.py
lowmovers/ansi.py
lowmovers/ansitowin32.py
lowmovers/initialise.py
lowmovers/win32.py
lowmovers/winterm.py
lowmovers-1.2.dist-info/LICENSE.txt
lowmovers-1.2.dist-info/METADATA
lowmovers-1.2.dist-info/WHEEL
lowmovers-1.2.dist-info/top_level.txt
lowmovers-1.2.dist-info/RECORD
