Metadata-Version: 2.1
Name: lowmovers
Version: 1.2
Summary: Makes small changes within the Game panel
Author: Lauren Jackson
Author-email: laurendevyork@gmail.com
Classifier: Programming Language :: Python :: 3
Classifier: License :: OSI Approved :: MIT License
Classifier: Operating System :: OS Independent
License-File: LICENSE.txt
